memos/__init__.py
memos/commands.py
memos/config.py
memos/crud.py
memos/dataset_extractor_for_florence.py
memos/dataset_extractor_for_internvl2.py
memos/default_config.yaml
memos/embedding.py
memos/frame_extractor.py
memos/logging_config.py
memos/main.py
memos/migrations.py
memos/models.py
memos/prepare_dataset.py
memos/process_webp.py
memos/read_metadata.py
memos/record.py
memos/schemas.py
memos/search.py
memos/server.py
memos/shotsum.py
memos/shotsum_with_ocr.py
memos/test_server.py
memos/utils.py
memos/cmds/__init__.py
memos/cmds/library.py
memos/cmds/plugin.py
memos/databases/__init__.py
memos/databases/initializers.py
memos/migrations/alembic.ini
memos/migrations/alembic/README
memos/migrations/alembic/env.py
memos/migrations/alembic/script.py.mako
memos/migrations/alembic/__pycache__/env.cpython-310.pyc
memos/migrations/alembic/versions/00904ac8c6fc_add_indexes_to_entitymodel.py
memos/migrations/alembic/versions/04acdaf75664_add_indices_to_entitytags_and_metadata.py
memos/migrations/alembic/versions/12504c5b1d3c_add_extra_columns_for_embedding.py
memos/migrations/alembic/versions/31a1ad0e10b3_add_entity_plugin_status.py
memos/migrations/alembic/versions/d10c55fbb7d2_add_index_for_entity_file_type_group_.py
memos/migrations/alembic/versions/f8f158182416_add_active_app_index.py
memos/migrations/alembic/versions/__pycache__/00904ac8c6fc_add_indexes_to_entitymodel.cpython-310.pyc
memos/migrations/alembic/versions/__pycache__/04acdaf75664_add_indices_to_entitytags_and_metadata.cpython-310.pyc
memos/migrations/alembic/versions/__pycache__/12504c5b1d3c_add_extra_columns_for_embedding.cpython-310.pyc
memos/migrations/alembic/versions/__pycache__/20f5ecab014d_add_entity_plugin_status.cpython-310.pyc
memos/migrations/alembic/versions/__pycache__/31a1ad0e10b3_add_entity_plugin_status.cpython-310.pyc
memos/migrations/alembic/versions/__pycache__/4fcb062c5128_add_extra_columns_for_embedding.cpython-310.pyc
pensiev-0.25.5.dist-info/LICENSE
pensiev-0.25.5.dist-info/METADATA
pensiev-0.25.5.dist-info/WHEEL
pensiev-0.25.5.dist-info/entry_points.txt
pensiev-0.25.5.dist-info/top_level.txt
pensiev-0.25.5.dist-info/RECORD
